minecraftverse/__init__.py
minecraftverse/api_client.py
minecraftverse/api_response.py
minecraftverse/configuration.py
minecraftverse/exceptions.py
minecraftverse/py.typed
minecraftverse/rest.py
minecraftverse/api/__init__.py
minecraftverse/api/default_api.py
minecraftverse/models/__init__.py
minecraftverse/models/download.py
minecraftverse/models/version.py
minecraftverse/models/version_manifest.py
minecraftverse/models/version_manifest_latest.py
minecraftverse/models/version_package_info.py
minecraftverse/models/version_package_info_asset_index.py
minecraftverse/models/version_package_info_downloads.py
minecraftverse/models/version_package_info_java_version.py
minecraftverse-1.2.0.dist-info/METADATA
minecraftverse-1.2.0.dist-info/WHEEL
minecraftverse-1.2.0.dist-info/top_level.txt
minecraftverse-1.2.0.dist-info/RECORD
