Metadata-Version: 2.4
Name: minecraftverse
Version: 1.2.0
Home-page: https://github.com/oapicf/minecraft-versions
Author: Minecraft Versions
Author-email: Minecraft Versions <blah+oapicf@cliffano.com>
License: MIT
Project-URL: Repository, https://github.com/oapicf/minecraft-versions
Keywords: OpenAPI,OpenAPI-Generator,
Requires-Python: >=3.9
Requires-Dist: urllib3<3.0.0,>=2.1.0
Requires-Dist: python-dateutil>=2.8.2
Requires-Dist: pydantic>=2
Requires-Dist: typing-extensions>=4.7.1
Dynamic: author
Dynamic: home-page
